code_parser/__init__.py
code_parser/__main__.py
code_parser/config.py
code_parser/core.py
code_parser-0.0.2.dist-info/LICENSE
code_parser-0.0.2.dist-info/METADATA
code_parser-0.0.2.dist-info/WHEEL
code_parser-0.0.2.dist-info/top_level.txt
code_parser-0.0.2.dist-info/RECORD
