Metadata-Version: 2.1
Name: code-parser
Version: 0.0.2
Summary: UNKNOWN
Home-page: https://github.com/ilearnToday/FirstOtusHomework
Author: Viatcheslav ilearnToday
Author-email: goodeitime@gmail.com
License: UNKNOWN
Platform: UNKNOWN
Classifier: Programming Language :: Python :: 3
Classifier: License :: OSI Approved :: MIT License
Classifier: Operating System :: OS Independent
